fieldday/__init__.py
fieldday/fieldclasses.py
fieldday/fieldset.py
fieldday/helpers.py
fieldday-1.0.0.dist-info/LICENSE
fieldday-1.0.0.dist-info/METADATA
fieldday-1.0.0.dist-info/WHEEL
fieldday-1.0.0.dist-info/top_level.txt
fieldday-1.0.0.dist-info/RECORD
