Metadata-Version: 2.1
Name: fieldday
Version: 1.0.0
Summary: package for managing lists of fields for IoT
Home-page: https://github.com/jmfife/fieldday
Author: Mike Fife
Author-email: "J. M. Fife" <jmfife@gmail.com>
License: MIT
Classifier: Programming Language :: Python :: 3
Classifier: License :: OSI Approved :: MIT License
Classifier: Operating System :: OS Independent
Requires-Python: >=3.7
License-File: LICENSE
Requires-Dist: pint (>=1.17)
Provides-Extra: qty
Requires-Dist: pint ; extra == 'qty'
